{
  "runtime": "kotlin",
  "version": "1.0.0",
  "source": "manually curated",
  "practices": [
    {
      "id": "kt-001",
      "title": "Never hardcode secrets in source code",
      "cwe": 798,
      "dimension": "security",
      "severity": "critical",
      "bad": "val apiKey = \"sk-prod-abc123xyz456\"",
      "good": "val apiKey = System.getenv(\"API_KEY\")",
      "explanation": "Hardcoded secrets are committed to version control and exposed in logs. Always read from environment variables or a secrets manager."
    },
    {
      "id": "kt-002",
      "title": "Use parameterized queries — never string-template SQL",
      "cwe": 89,
      "dimension": "security",
      "severity": "high",
      "bad": "db.query(\"SELECT * FROM users WHERE id = ${userId}\")",
      "good": "db.query(\"SELECT * FROM users WHERE id = ?\", listOf(userId))",
      "explanation": "String-templated SQL enables injection attacks. Use parameterized queries or an ORM's safe query builder."
    },
    {
      "id": "kt-003",
      "title": "Validate external input before processing",
      "cwe": 20,
      "dimension": "security",
      "severity": "high",
      "bad": "fun handleRequest(body: String) {\n    val user = Json.decodeFromString<User>(body)\n    db.save(user)\n}",
      "good": "fun handleRequest(body: String) {\n    val user = Json.decodeFromString<User>(body)\n    require(user.name.isNotBlank()) { \"Name is required\" }\n    db.save(user)\n}",
      "explanation": "Unvalidated input leads to injection and data corruption. Validate at API boundaries using require/check."
    },
    {
      "id": "kt-004",
      "title": "Never use Runtime.exec with unsanitized input",
      "cwe": 78,
      "dimension": "security",
      "severity": "high",
      "bad": "Runtime.getRuntime().exec(\"sh -c $userInput\")",
      "good": "ProcessBuilder(\"sh\", \"-c\", sanitizedCmd).start()",
      "explanation": "Constructing shell commands from user input enables command injection. Use ProcessBuilder with argument arrays."
    },
    {
      "id": "kt-005",
      "title": "Use data classes for DTOs and value objects",
      "cwe": 1061,
      "dimension": "maintainability",
      "severity": "medium",
      "bad": "class User {\n    var name: String = \"\"\n    var email: String = \"\"\n    override fun equals(other: Any?): Boolean { ... }\n    override fun hashCode(): Int { ... }\n}",
      "good": "data class User(val name: String, val email: String)",
      "explanation": "Data classes auto-generate equals, hashCode, toString, and copy. Manual implementations are error-prone and verbose."
    },
    {
      "id": "kt-006",
      "title": "Use sealed classes for restricted type hierarchies",
      "cwe": 1061,
      "dimension": "maintainability",
      "severity": "medium",
      "bad": "open class Result\nclass Success(val data: String) : Result()\nclass Failure(val error: String) : Result()",
      "good": "sealed class Result {\n    data class Success(val data: String) : Result()\n    data class Failure(val error: String) : Result()\n}",
      "explanation": "Sealed classes ensure exhaustive when-expressions and prevent unexpected subtypes from being added outside the file."
    },
    {
      "id": "kt-007",
      "title": "Prefer extension functions over utility classes",
      "cwe": 1061,
      "dimension": "maintainability",
      "severity": "low",
      "bad": "object StringUtils {\n    fun isEmail(s: String): Boolean = s.contains(\"@\")\n}",
      "good": "fun String.isEmail(): Boolean = contains(\"@\")",
      "explanation": "Extension functions are more idiomatic in Kotlin and discoverable via IDE autocomplete. Avoid Java-style static utility classes."
    },
    {
      "id": "kt-008",
      "title": "Keep files under 300 lines",
      "cwe": 1080,
      "dimension": "maintainability",
      "severity": "medium",
      "bad": "// 500-line file mixing data classes, business logic, and API calls",
      "good": "// Separate into UserModel.kt, UserService.kt, UserController.kt",
      "explanation": "Large files violate Single Responsibility Principle and are hard to navigate and test."
    },
    {
      "id": "kt-009",
      "title": "Use runCatching for recoverable operations",
      "cwe": 755,
      "dimension": "reliability",
      "severity": "medium",
      "bad": "try {\n    val data = fetchRemote()\n    process(data)\n} catch (e: Exception) {\n    log(e)\n}",
      "good": "runCatching { fetchRemote() }\n    .onSuccess { process(it) }\n    .onFailure { logger.error(\"Fetch failed\", it) }",
      "explanation": "runCatching provides a functional error-handling pattern with map/recover chains. Avoids broad catch blocks."
    },
    {
      "id": "kt-010",
      "title": "Never swallow exceptions with empty catch blocks",
      "cwe": 390,
      "dimension": "reliability",
      "severity": "medium",
      "bad": "try { riskyOp() } catch (e: Exception) { }",
      "good": "try { riskyOp() } catch (e: Exception) { logger.error(\"Failed\", e) }",
      "explanation": "Empty catch blocks hide errors and make debugging impossible. At minimum log the exception."
    },
    {
      "id": "kt-011",
      "title": "Handle coroutine exceptions with CoroutineExceptionHandler",
      "cwe": 755,
      "dimension": "reliability",
      "severity": "high",
      "bad": "GlobalScope.launch {\n    riskyOperation()\n}",
      "good": "val handler = CoroutineExceptionHandler { _, e -> logger.error(\"Coroutine failed\", e) }\nscope.launch(handler) {\n    riskyOperation()\n}",
      "explanation": "Uncaught coroutine exceptions crash the app or are silently lost. Use structured concurrency with exception handlers."
    },
    {
      "id": "kt-012",
      "title": "Use safe calls and Elvis operator for nullable handling",
      "cwe": 476,
      "dimension": "reliability",
      "severity": "medium",
      "bad": "val name = user!!.name!!",
      "good": "val name = user?.name ?: \"Unknown\"",
      "explanation": "Force unwrap (!!) crashes at runtime on null. Use safe calls (?.) and Elvis (?:) for null-safe access."
    },
    {
      "id": "kt-013",
      "title": "Use sequences for large collection pipelines",
      "cwe": 400,
      "dimension": "performance",
      "severity": "medium",
      "bad": "val result = hugeList\n    .filter { it.isActive }\n    .map { transform(it) }\n    .take(10)",
      "good": "val result = hugeList.asSequence()\n    .filter { it.isActive }\n    .map { transform(it) }\n    .take(10)\n    .toList()",
      "explanation": "Collection operations create intermediate lists at each step. Sequences evaluate lazily, processing one element at a time."
    },
    {
      "id": "kt-014",
      "title": "Use appropriate coroutine dispatchers",
      "cwe": 1088,
      "dimension": "performance",
      "severity": "high",
      "bad": "withContext(Dispatchers.Main) {\n    val data = readLargeFile()\n}",
      "good": "withContext(Dispatchers.IO) {\n    val data = readLargeFile()\n}",
      "explanation": "IO-bound work on Main dispatcher blocks the UI thread. Use Dispatchers.IO for file/network operations and Default for CPU-bound work."
    },
    {
      "id": "kt-015",
      "title": "Avoid unnecessary object allocation in hot paths",
      "cwe": 1050,
      "dimension": "performance",
      "severity": "medium",
      "bad": "fun formatItems(items: List<Item>): String {\n    var result = \"\"\n    items.forEach { result += \"${it.name},\" }\n    return result\n}",
      "good": "fun formatItems(items: List<Item>): String =\n    items.joinToString(\",\") { it.name }",
      "explanation": "String concatenation in loops creates O(n) intermediate String objects. Use joinToString or StringBuilder."
    },
    {
      "id": "kt-016",
      "title": "Avoid N+1 queries — batch database access",
      "cwe": 1084,
      "dimension": "performance",
      "severity": "high",
      "bad": "for (user in users) {\n    val orders = orderRepo.findByUserId(user.id)\n}",
      "good": "val ids = users.map { it.id }\nval orders = orderRepo.findByUserIds(ids)",
      "explanation": "Querying inside a loop creates N+1 round-trips. Batch into a single query with IN clause."
    }
  ]
}
